DacuBeihouDeQianduanHexinYewuShijian/README.md
DacuBeihouDeQianduanHexinYewuShijian/__init__.py
DacuBeihouDeQianduanHexinYewuShijian/__main__.py
DacuBeihouDeQianduanHexinYewuShijian/file.pdf
DacuBeihouDeQianduanHexinYewuShijian/index.html
dacu_beihou_de_qianduan_hexin_yewu_shijian-2024.3.5.0.dist-info/METADATA
dacu_beihou_de_qianduan_hexin_yewu_shijian-2024.3.5.0.dist-info/WHEEL
dacu_beihou_de_qianduan_hexin_yewu_shijian-2024.3.5.0.dist-info/entry_points.txt
dacu_beihou_de_qianduan_hexin_yewu_shijian-2024.3.5.0.dist-info/top_level.txt
dacu_beihou_de_qianduan_hexin_yewu_shijian-2024.3.5.0.dist-info/RECORD
